pyamps/__init__.py
pyamps/amps.py
pyamps/mlt_utils.py
pyamps/model_utils.py
pyamps/model_vector_to_txt.py
pyamps/plot_utils.py
pyamps/sh_utils.py
pyamps/coefficients/SW_OPER_MIO_SHA_2E_00000000T000000_99999999T999999_0101.txt
pyamps/coefficients/SW_OPER_MIO_SHA_2E_00000000T000000_99999999T999999_0102.txt
pyamps/coefficients/SW_OPER_MIO_SHA_2E_00000000T000000_99999999T999999_0103.txt
pyamps/coefficients/SW_OPER_MIO_SHA_2E_00000000T000000_99999999T999999_0104.txt
pyamps/coefficients/SW_OPER_MIO_SHA_2E_00000000T000000_99999999T999999_0105.txt
pyamps/coefficients/__init__.py
pyamps/coefficients/model_vector_NT_MT_NV_MV_65_3_45_3.npy
pyamps/coefficients/model_vector_NT_MT_NV_MV_65_3_45_3__v1.0.npy
pyamps/coefficients/model_vector_NT_MT_NV_MV_65_3_45_3__v1.1.npy
pyamps/coefficients/model_vector_NT_MT_NV_MV_65_3_45_3__v1.3.npy
pyamps/coefficients/model_vector_NT_MT_NV_MV_65_3_45_3__v1.4.npy
pyamps/coefficients/model_vector_NT_MT_NV_MV_65_3_45_3__v1.5.npy
pyamps/coefficients/test_model.txt
pyamps-1.7.0.dist-info/licenses/LICENSE
pyamps-1.7.0.dist-info/METADATA
pyamps-1.7.0.dist-info/WHEEL
pyamps-1.7.0.dist-info/top_level.txt
pyamps-1.7.0.dist-info/RECORD
