Metadata-Version: 2.4
Name: pyamps
Version: 1.7.0
Summary: Calculate and plot maps of the model Average Magnetic field and Polar current System (AMPS)
Home-page: https://github.com/klaundal/pyAMPS
Author: Karl M. Laundal
Author-email: karl.laundal@ift.uib.no
License: MIT
Keywords: AMPS,Average Magnetic field and Polar current System,magnetic field,spherical harmonics model,associated Legendre polynomial,mlt,magnetic local time,subsolar,dipole coordinates,converting
Classifier: Development Status :: 5 - Production/Stable
Classifier: Intended Audience :: Science/Research
Classifier: License :: OSI Approved :: MIT License
Classifier: Operating System :: Unix
Classifier: Operating System :: POSIX
Classifier: Operating System :: Microsoft :: Windows
Classifier: Programming Language :: Python
Classifier: Programming Language :: Python :: 3
Classifier: Programming Language :: Python :: 3.4
Classifier: Programming Language :: Python :: 3.5
Classifier: Programming Language :: Python :: 3.6
Classifier: Topic :: Scientific/Engineering :: Physics
License-File: LICENSE
Requires-Dist: setuptools>=30.3.0
Requires-Dist: future>=0.16
Requires-Dist: numpy>=1.14
Requires-Dist: matplotlib
Requires-Dist: scipy>=0.9
Requires-Dist: toolz>=0.8
Requires-Dist: pandas>=0.20
Requires-Dist: dask
Requires-Dist: apexpy>=1.0
Provides-Extra: dev
Requires-Dist: sphinx>=1.3; extra == "dev"
Requires-Dist: sphinx_pypi_upload; extra == "dev"
Provides-Extra: test
Requires-Dist: pytest; extra == "test"
Dynamic: license-file
